{
  "schema_version": "0.1",
  "run_id": "run-invalid-executor-final-verdict",
  "project_id": "devframe-system",
  "goal_id": "goal-runtime-governance-batch-a",
  "task_id": "task-run-record-contract",
  "attempt_id": "attempt-1",
  "context_packet_id": "cp-batch-a-context-v1",
  "context_ledger_id": "cl-batch-a-context-v1",
  "domain": "code",
  "profile": "contract-only",
  "producer_role": "runtime_adapter",
  "created_at": "2026-07-07T00:00:00Z",
  "updated_at": "2026-07-07T00:00:00Z",
  "phase": "closed",
  "outcome": "passed",
  "review_state": "review_passed",
  "gate_state": "gate_passed",
  "acceptance_state": "final_ready",
  "projection_state": "completed",
  "worker_results": [
    {
      "worker_id": "worker-schema-slice",
      "worker_role": "worker",
      "status": "completed",
      "reported_at": "2026-07-07T00:00:00Z"
    }
  ],
  "artifact_refs": [],
  "evidence_refs": [
    {
      "evidence_id": "e-runrecord-schema",
      "kind": "other",
      "uri": "schemas/runtime-governance/run-record.schema.json",
      "supports": "gate"
    }
  ],
  "review_refs": [
    {
      "review_id": "review-independent",
      "reviewer_id": "reviewer-1",
      "reviewer_role": "reviewer",
      "verdict": "pass",
      "uri": "reviews/independent-review.yaml",
      "reviewed_evidence_refs": [
        "e-runrecord-schema"
      ]
    }
  ],
  "gate_refs": [
    {
      "gate_id": "gate-public-snapshot",
      "result": "pass",
      "uri": "reports/public-snapshot.txt",
      "evidence_refs": [
        "e-runrecord-schema"
      ]
    }
  ],
  "failure_refs": [],
  "final_verdict_ref": {
    "verdict_id": "fv-invalid-executor",
    "producer_role": "executor",
    "final_state": "final_ready",
    "uri": "final-verdict.json",
    "review_ref": "review-independent",
    "gate_refs": [
      "gate-public-snapshot"
    ]
  },
  "domain_refs": {}
}
